maif_api.py
maif/__init__.py
maif/cli.py
maif-0.1.2.dist-info/licenses/LICENSE
maif-0.1.2.dist-info/METADATA
maif-0.1.2.dist-info/WHEEL
maif-0.1.2.dist-info/entry_points.txt
maif-0.1.2.dist-info/top_level.txt
maif-0.1.2.dist-info/RECORD
