Metadata-Version: 2.4
Name: maif
Version: 0.1.2
Summary: Multimodal Artifact File Format - Production-ready AI-native container with trustworthy AI capabilities
Home-page: https://github.com/vineethsai/maif
Author: MAIF Development Team
Author-email: MAIF Development Team <dev@maif.ai>
Maintainer-email: MAIF Development Team <dev@maif.ai>
License: MIT
Project-URL: Homepage, https://github.com/vineethsai/maif
Project-URL: Documentation, https://vineethsai.github.io/maif/
Project-URL: Repository, https://github.com/vineethsai/maif
Project-URL: Bug Reports, https://github.com/vineethsai/maif/issues
Project-URL: Changelog, https://github.com/vineethsai/maif/blob/main/CHANGELOG.md
Keywords: ai,multimodal,security,provenance,forensics,trustworthy-ai,file-format,compression,streaming,cross-modal,attention,semantic,cryptography,aws,cloud,production,enterprise
Classifier: Development Status :: 5 - Production/Stable
Classifier: Intended Audience :: Developers
Classifier: Intended Audience :: Science/Research
Classifier: License :: OSI Approved :: MIT License
Classifier: Operating System :: OS Independent
Classifier: Programming Language :: Python :: 3
Classifier: Programming Language :: Python :: 3.9
Classifier: Programming Language :: Python :: 3.10
Classifier: Programming Language :: Python :: 3.11
Classifier: Programming Language :: Python :: 3.12
Classifier: Topic :: Scientific/Engineering :: Artificial Intelligence
Classifier: Topic :: Security :: Cryptography
Classifier: Topic :: Software Development :: Libraries :: Python Modules
Classifier: Topic :: System :: Archiving
Classifier: Topic :: Software Development :: Version Control
Classifier: Topic :: System :: Distributed Computing
Requires-Python: >=3.8
License-File: LICENSE
Requires-Dist: numpy>=1.21.0
Requires-Dist: cryptography>=3.4.8
Requires-Dist: scikit-learn>=1.0.0
Requires-Dist: pydantic>=2.0.0
Requires-Dist: structlog>=23.0.0
Requires-Dist: tenacity>=8.0.0
Provides-Extra: full
Requires-Dist: boto3>=1.26.0; extra == "full"
Requires-Dist: botocore>=1.29.0; extra == "full"
Requires-Dist: sentence-transformers>=2.2.0; extra == "full"
Requires-Dist: faiss-cpu>=1.7.0; extra == "full"
Requires-Dist: opencv-python>=4.5.0; extra == "full"
Requires-Dist: aiofiles>=0.8.0; extra == "full"
Requires-Dist: brotli>=1.0.9; extra == "full"
Requires-Dist: zstandard>=0.18.0; extra == "full"
Requires-Dist: xxhash>=3.0.0; extra == "full"
Requires-Dist: msgpack>=1.0.4; extra == "full"
Requires-Dist: jsonschema>=4.0.0; extra == "full"
Requires-Dist: click>=8.0.0; extra == "full"
Requires-Dist: tqdm>=4.64.0; extra == "full"
Requires-Dist: psutil>=5.8.0; extra == "full"
Requires-Dist: networkx>=2.6.0; extra == "full"
Requires-Dist: matplotlib>=3.4.0; extra == "full"
Requires-Dist: pillow>=8.3.0; extra == "full"
Requires-Dist: scipy>=1.7.0; extra == "full"
Requires-Dist: lz4>=4.0.0; extra == "full"
Requires-Dist: numba>=0.56.0; extra == "full"
Requires-Dist: prometheus-client>=0.16.0; extra == "full"
Provides-Extra: production
Requires-Dist: boto3>=1.26.0; extra == "production"
Requires-Dist: botocore>=1.29.0; extra == "production"
Requires-Dist: prometheus-client>=0.16.0; extra == "production"
Requires-Dist: aiofiles>=0.8.0; extra == "production"
Requires-Dist: jsonschema>=4.0.0; extra == "production"
Requires-Dist: psutil>=5.8.0; extra == "production"
Requires-Dist: tenacity>=8.0.0; extra == "production"
Requires-Dist: structlog>=23.0.0; extra == "production"
Provides-Extra: aws
Requires-Dist: boto3>=1.26.0; extra == "aws"
Requires-Dist: botocore>=1.29.0; extra == "aws"
Provides-Extra: dev
Requires-Dist: pytest>=6.0.0; extra == "dev"
Requires-Dist: pytest-cov>=2.12.0; extra == "dev"
Requires-Dist: pytest-asyncio>=0.21.0; extra == "dev"
Requires-Dist: black>=21.0.0; extra == "dev"
Requires-Dist: flake8>=3.9.0; extra == "dev"
Requires-Dist: mypy>=1.0.0; extra == "dev"
Requires-Dist: pre-commit>=2.15.0; extra == "dev"
Requires-Dist: moto>=4.0.0; extra == "dev"
Requires-Dist: pytest-mock>=3.10.0; extra == "dev"
Provides-Extra: compression
Requires-Dist: brotli>=1.0.9; extra == "compression"
Requires-Dist: zstandard>=0.18.0; extra == "compression"
Requires-Dist: lz4>=4.0.0; extra == "compression"
Provides-Extra: async
Requires-Dist: aiofiles>=0.8.0; extra == "async"
Provides-Extra: cli
Requires-Dist: click>=8.0.0; extra == "cli"
Requires-Dist: tqdm>=4.64.0; extra == "cli"
Provides-Extra: validation
Requires-Dist: jsonschema>=4.0.0; extra == "validation"
Requires-Dist: pydantic>=2.0.0; extra == "validation"
Provides-Extra: performance
Requires-Dist: xxhash>=3.0.0; extra == "performance"
Requires-Dist: msgpack>=1.0.4; extra == "performance"
Requires-Dist: psutil>=5.8.0; extra == "performance"
Requires-Dist: numba>=0.56.0; extra == "performance"
Provides-Extra: ml
Requires-Dist: sentence-transformers>=2.2.0; extra == "ml"
Requires-Dist: faiss-cpu>=1.7.0; extra == "ml"
Requires-Dist: scipy>=1.7.0; extra == "ml"
Provides-Extra: vision
Requires-Dist: opencv-python>=4.5.0; extra == "vision"
Requires-Dist: pillow>=8.3.0; extra == "vision"
Provides-Extra: monitoring
Requires-Dist: prometheus-client>=0.16.0; extra == "monitoring"
Provides-Extra: integrations
Requires-Dist: langgraph>=0.2.0; extra == "integrations"
Requires-Dist: langgraph-checkpoint>=1.0.0; extra == "integrations"
Requires-Dist: langchain-core>=0.3.0; extra == "integrations"
Requires-Dist: langchain-google-genai>=2.0.0; extra == "integrations"
Requires-Dist: crewai>=0.30.0; extra == "integrations"
Requires-Dist: google-generativeai>=0.3.0; extra == "integrations"
Dynamic: author
Dynamic: home-page
Dynamic: license-file
Dynamic: requires-python
